features/__init__.py
features/benchmark.py
features/high_low_voice.py
features/loudness.py
features/out_key.py
features/polyphony.py
features/repeat_merge.py
features/rhythm.py
features/specific_pitch.py
features/utils.py
peamt-0.2.0.dist-info/LICENSE
peamt-0.2.0.dist-info/METADATA
peamt-0.2.0.dist-info/WHEEL
peamt-0.2.0.dist-info/top_level.txt
peamt-0.2.0.dist-info/RECORD
