Metadata-Version: 2.1
Name: peamt
Version: 0.2.0
Summary: PEAMT: a Perceptual Evaluation metric for Automatic Music Transcription
Home-page: https://github.com/adrienycart/PEAMT
Author: Adrien Ycart
Author-email: adrien.ycart@gmail.com
License: UNKNOWN
Project-URL: Bug Tracker, https://github.com/adrienycart/PEAMT/issues
Platform: UNKNOWN
Classifier: Programming Language :: Python :: 3
Classifier: License :: OSI Approved :: MIT License
Classifier: Operating System :: OS Independent
Requires-Dist: numpy
Requires-Dist: pretty-midi (==0.2.8)
Requires-Dist: mir-eval
